LICENSE
README.md
setup.py
magicaltools/__init__.py
magicaltools/mp34.py
magicaltools.egg-info/PKG-INFO
magicaltools.egg-info/SOURCES.txt
magicaltools.egg-info/dependency_links.txt
magicaltools.egg-info/top_level.txt
magicaltools.egg-info/zip-safe